MANIFEST.in
README.md
setup.cfg
setup.py
bridgy/__init__.py
bridgy/__main__.py
bridgy/error.py
bridgy/tmux.py
bridgy/utils.py
bridgy/version.py
bridgy.egg-info/PKG-INFO
bridgy.egg-info/SOURCES.txt
bridgy.egg-info/dependency_links.txt
bridgy.egg-info/entry_points.txt
bridgy.egg-info/not-zip-safe
bridgy.egg-info/requires.txt
bridgy.egg-info/top_level.txt
bridgy/command/__init__.py
bridgy/command/ansible_utils.py
bridgy/command/run.py
bridgy/command/ssh.py
bridgy/command/sshfs.py
bridgy/config/__init__.py
bridgy/config/base.py
bridgy/config/v1.py
bridgy/config/v2.py
bridgy/config/samples/sample_config_1.yml
bridgy/config/samples/sample_config_2.yml
bridgy/inventory/__init__.py
bridgy/inventory/aws.py
bridgy/inventory/flatfile.py
bridgy/inventory/newrelic.py
bridgy/inventory/source.py