Metadata-Version: 1.1
Name: bridgy
Version: 0.2.1
Summary: Easily search your cloud inventory and integrate with ssh + tmux + sshfs
Home-page: https://github.com/wagoodman/bridgy
Author: Alex Goodman
Author-email: wagoodman@gmail.com
License: MIT
Keywords: tmux,ssh,sshfs,aws,newrelic,inventory,cloud
Platform: linux
Classifier: Development Status :: 4 - Beta
Classifier: Environment :: Console
Classifier: Intended Audience :: Developers
Classifier: License :: OSI Approved :: MIT License
Classifier: Natural Language :: English
Classifier: Operating System :: POSIX :: Linux
Classifier: Programming Language :: Python
Classifier: Programming Language :: Python :: 2
Classifier: Programming Language :: Python :: 3
Classifier: Programming Language :: Python :: Implementation :: CPython
Classifier: Topic :: Software Development :: Libraries :: Python Modules
Classifier: Topic :: System :: Monitoring
Classifier: Topic :: System :: Systems Administration
Classifier: Topic :: System :: System Shells
Classifier: Topic :: Terminals
Classifier: Topic :: Utilities
